outerspace/__init__.py
outerspace/tsne_playground.py
outerspace-0.1.0.dist-info/LICENSE
outerspace-0.1.0.dist-info/METADATA
outerspace-0.1.0.dist-info/WHEEL
outerspace-0.1.0.dist-info/top_level.txt
outerspace-0.1.0.dist-info/RECORD
