Metadata-Version: 2.1
Name: outerspace
Version: 0.1.0
Summary: UNKNOWN
Home-page: https://github.com/sirbiscuit/outerspace
Author: sirbiscuit
License: MIT
Platform: UNKNOWN
Requires-Dist: opentsne (~=0.3.8)
Requires-Dist: ipywidgets (~=7.4.2)
Requires-Dist: bokeh (~=1.2.0)
